{
  "id": "level8",
  "name": "Last Light",
  "background": "nb_crimsonstorm",
  "music": "space_boss_battle_bpm175.ogg",
  "difficulty": "Ultimate",
  "description": "Final combined-arms assault. Survive layered threats to reach the command core.",
  "completeOnBoss": true,
  "enemyTypes": {
    "gnat": {
      "sprite": "enemyRed2",
      "hull": 16,
      "shield": 0,
      "armor": 0,
      "speed": 182,
      "score": 72,
      "baseCredit": 10,
      "radius": 12,
      "pattern": "laneShift",
      "patternParams": {
        "amplitude": 205,
        "frequency": 6,
        "shiftEvery": 0.8,
        "shiftSpeed": 6.8
      }
    },
    "dart": {
      "sprite": "enemyBlue2",
      "hull": 24,
      "shield": 0,
      "armor": 0,
      "speed": 170,
      "score": 108,
      "baseCredit": 12,
      "radius": 16,
      "pattern": "spiralIn",
      "patternParams": {
        "amplitude": 190,
        "frequency": 5.9,
        "decay": 0.14
      }
    },
    "spark": {
      "sprite": "enemyGreen4",
      "hull": 20,
      "shield": 42,
      "armor": 0,
      "speed": 160,
      "score": 160,
      "baseCredit": 18,
      "radius": 18,
      "pattern": "laneShift",
      "fireRate": 1.6,
      "fireMode": "spread",
      "fireCount": 5,
      "fireSpread": 0.9,
      "shieldRegen": 14,
      "patternParams": {
        "shiftEvery": 0.9,
        "shiftSpeed": 6.2
      }
    },
    "skitter": {
      "sprite": "enemyBlue5",
      "hull": 32,
      "shield": 0,
      "armor": 0,
      "speed": 142,
      "score": 150,
      "baseCredit": 18,
      "radius": 18,
      "ai": "skitter",
      "aiParams": {
        "dodgeRadius": 160,
        "dodgeStrength": 1.75
      },
      "fireRate": 1.4,
      "fireMode": "spread",
      "fireCount": 3,
      "fireSpread": 0.56,
      "bulletSpeed": 190
    },
    "sentinel": {
      "sprite": "enemyBlack3",
      "hull": 44,
      "shield": 60,
      "armor": 0,
      "speed": 90,
      "score": 190,
      "baseCredit": 24,
      "radius": 22,
      "ai": "sentinel",
      "aiParams": {
        "holdY": 138,
        "slideSpeed": 1.03,
        "keepOut": 165
      },
      "fireRate": 1.2,
      "fireMode": "aim",
      "bulletSpeed": 210
    },
    "stalker": {
      "sprite": "enemyBlue5",
      "hull": 46,
      "shield": 34,
      "armor": 0,
      "speed": 130,
      "score": 290,
      "baseCredit": 34,
      "radius": 18,
      "ai": "stalker",
      "aggroRadius": 240,
      "fireRate": 1.35,
      "fireMode": "aim",
      "shieldRegen": 10
    },
    "duelist": {
      "sprite": "enemyRed5",
      "hull": 50,
      "shield": 0,
      "armor": 176,
      "armorClass": 14,
      "speed": 94,
      "score": 230,
      "baseCredit": 28,
      "radius": 20,
      "ai": "duelist",
      "aiParams": {
        "holdY": 190,
        "standoff": 240,
        "strafeSpeed": 1.08
      },
      "fireRate": 1.3,
      "fireMode": "aim",
      "bulletSpeed": 215
    },
    "escort": {
      "sprite": "enemyBlack3",
      "hull": 52,
      "shield": 0,
      "armor": 220,
      "armorClass": 15,
      "speed": 56,
      "score": 250,
      "baseCredit": 30,
      "radius": 20,
      "pattern": "stall",
      "fireMode": "spread",
      "fireCount": 5,
      "fireSpread": 0.9,
      "fireRate": 1.9,
      "patternParams": {
        "stallY": 172,
        "stallDuration": 2,
        "strafeAmp": 120,
        "strafeFreq": 1.5
      }
    },
    "tank": {
      "sprite": "ufoYellow",
      "hull": 86,
      "shield": 0,
      "armor": 500,
      "armorClass": 19,
      "speed": 24,
      "score": 340,
      "baseCredit": 42,
      "radius": 30,
      "ai": "transport",
      "fireMode": "aim",
      "fireRate": 3,
      "bulletSpeed": 160
    },
    "bulwark": {
      "sprite": "ufoBlue",
      "hull": 122,
      "shield": 0,
      "armor": 900,
      "armorClass": 22,
      "speed": 18,
      "score": 420,
      "baseCredit": 52,
      "radius": 34,
      "ai": "transport",
      "fireRate": 3.2
    },
    "hunter": {
      "sprite": "enemyGreen4",
      "hull": 52,
      "shield": 0,
      "armor": 44,
      "armorClass": 6,
      "speed": 142,
      "score": 250,
      "baseCredit": 32,
      "radius": 20,
      "ai": "hunter",
      "fireRate": 1.55
    },
    "boss": {
      "sprite": "assets/generated/boss_anvil.png",
      "hull": 1680,
      "shield": 1040,
      "armor": 1240,
      "armorClass": 16,
      "shieldRegen": 20,
      "speed": 124,
      "score": 6200,
      "baseCredit": 1450,
      "radius": 82,
      "pattern": "bossOrbit",
      "patternParams": {
        "warmupTime": 0.55,
        "radiusX": 340,
        "radiusY": 108,
        "orbitSpeed": 0.86,
        "wobble": 26
      },
      "isBoss": true,
      "empImmune": true,
      "fireRate": 0.46,
      "fireMode": "radial",
      "fireCount": 34,
      "bulletSpeed": 236,
      "spriteScale": 0.92
    }
  },
  "events": [
    {
      "time": 1,
      "type": "gnat",
      "count": 22,
      "interval": 0.16
    },
    {
      "time": 6,
      "type": "dart",
      "count": 16,
      "interval": 0.24
    },
    {
      "time": 11,
      "type": "spark",
      "count": 8,
      "interval": 0.6
    },
    {
      "time": 16,
      "type": "skitter",
      "count": 7,
      "interval": 0.58
    },
    {
      "time": 21,
      "type": "sentinel",
      "count": 6,
      "interval": 0.7
    },
    {
      "time": 26,
      "type": "stalker",
      "count": 5,
      "interval": 0.72
    },
    {
      "time": 31,
      "type": "duelist",
      "count": 6,
      "interval": 0.72
    },
    {
      "time": 36,
      "type": "escort",
      "count": 5,
      "interval": 0.76
    },
    {
      "time": 41,
      "type": "tank",
      "count": 2,
      "interval": 1.1
    },
    {
      "time": 46,
      "type": "bulwark",
      "count": 1
    },
    {
      "time": 50,
      "type": "hunter",
      "count": 5,
      "interval": 0.7
    },
    {
      "time": 54,
      "type": "gnat",
      "count": 24,
      "interval": 0.14
    },
    {
      "time": 58,
      "type": "dart",
      "count": 18,
      "interval": 0.2
    },
    {
      "time": 62,
      "type": "spark",
      "count": 9,
      "interval": 0.54
    },
    {
      "time": 66,
      "type": "skitter",
      "count": 8,
      "interval": 0.52
    },
    {
      "time": 70,
      "type": "sentinel",
      "count": 6,
      "interval": 0.66
    },
    {
      "time": 74,
      "type": "duelist",
      "count": 7,
      "interval": 0.66
    },
    {
      "time": 78,
      "type": "escort",
      "count": 6,
      "interval": 0.68
    },
    {
      "time": 82,
      "type": "tank",
      "count": 3,
      "interval": 1
    },
    {
      "time": 86,
      "type": "bulwark",
      "count": 2,
      "interval": 1.15
    },
    {
      "time": 90,
      "type": "hunter",
      "count": 6,
      "interval": 0.62
    },
    {
      "time": 98,
      "type": "boss",
      "count": 1
    }
  ]
}
